DynamicProcessWorker_preafixed/__init__.py
DynamicProcessWorker_preafixed/example/ExampleTask.py
DynamicProcessWorker_preafixed/example/ExampleWorker.py
DynamicProcessWorker_preafixed/example/__init__.py
DynamicProcessWorker_preafixed/gui/GuiStyling.py
DynamicProcessWorker_preafixed/gui/GuiUtils.py
DynamicProcessWorker_preafixed/gui/GuiWorker.py
DynamicProcessWorker_preafixed/gui/__init__.py
DynamicProcessWorker_preafixed/process/ProcessBalancer.py
DynamicProcessWorker_preafixed/process/ProcessManager.py
DynamicProcessWorker_preafixed/process/ProcessModel.py
DynamicProcessWorker_preafixed/process/ProcessWorker.py
DynamicProcessWorker_preafixed/process/__init__.py
DynamicProcessWorker_preafixed-1.0.7.dist-info/LICENSE
DynamicProcessWorker_preafixed-1.0.7.dist-info/METADATA
DynamicProcessWorker_preafixed-1.0.7.dist-info/WHEEL
DynamicProcessWorker_preafixed-1.0.7.dist-info/top_level.txt
DynamicProcessWorker_preafixed-1.0.7.dist-info/RECORD
