Metadata-Version: 2.1
Name: DynamicProcessWorker-preafixed
Version: 1.0.7
Summary: Python library for creating and managing Process Workers with an optional GUI
Author-email: Cem Bana <cembana.business@gmail.com>
License: MIT License        
Project-URL: Homepage, https://github.com/preafixed/Dynamic-Process-Worker
Classifier: Programming Language :: Python :: 3
Classifier: License :: OSI Approved :: MIT License
Classifier: Operating System :: OS Independent
Requires-Python: >=3.7
License-File: LICENSE
